addertestcode456.py
addertestcode456-0.0.1.dist-info/LICENSE
addertestcode456-0.0.1.dist-info/METADATA
addertestcode456-0.0.1.dist-info/WHEEL
addertestcode456-0.0.1.dist-info/top_level.txt
addertestcode456-0.0.1.dist-info/RECORD
